toyoildata/ToyOilSpillDataModule.py
toyoildata/ToyOilSpillDataset.py
toyoildata/__init__.py
toyoildata/utils.py
toyoildata-0.3.1.dist-info/METADATA
toyoildata-0.3.1.dist-info/WHEEL
toyoildata-0.3.1.dist-info/licenses/LICENSE
toyoildata-0.3.1.dist-info/RECORD
