Metadata-Version: 2.4
Name: toyoildata
Version: 0.3.1
Summary: Synthetic segmentation data with given TP, FP and FN small instances for visualization and testing of pipelines and metrics.
Author-email: Halyjo <35629262+Halyjo@users.noreply.github.com>
License-File: LICENSE
Requires-Python: >=3.10
Requires-Dist: lightning
Requires-Dist: matplotlib
Requires-Dist: numpy
Requires-Dist: opencv-python
Requires-Dist: pre-commit
Requires-Dist: torch
